docker_ps_cli/__init__.py
docker_ps_cli/__main__.py
docker_ps_cli/cli.py
docker_ps_cli/config.py
docker_ps_cli/utils/argparser.py
docker_ps_cli/utils/columns.py
docker_ps_cli/utils/filtering.py
docker_ps_cli/utils/logger.py
docker_ps_cli/utils/styling.py
docker_ps_cli-1.0.1.dist-info/licenses/LICENSE
docker_ps_cli-1.0.1.dist-info/METADATA
docker_ps_cli-1.0.1.dist-info/WHEEL
docker_ps_cli-1.0.1.dist-info/entry_points.txt
docker_ps_cli-1.0.1.dist-info/top_level.txt
docker_ps_cli-1.0.1.dist-info/RECORD
