Metadata-Version: 2.4
Name: docker-ps-cli
Version: 1.0.1
Summary: List your docker containers in a better way!
Author-email: Mert Emirimam <48881002+mertemr@users.noreply.github.com>
License-Expression: GPL-3.0-or-later
Project-URL: Homepage, https://github.com/mertemr/docker-ps-cli
Project-URL: Bug Tracker, https://github.com/mertemr/docker-ps-cli/issues
Keywords: docker,cli,containers
Classifier: Programming Language :: Python :: 3
Classifier: Programming Language :: Python :: 3.9
Classifier: Programming Language :: Python :: 3.10
Classifier: Programming Language :: Python :: 3.11
Classifier: Programming Language :: Python :: 3.12
Classifier: Operating System :: OS Independent
Classifier: Environment :: Console
Classifier: Topic :: Utilities
Requires-Python: >=3.9
License-File: LICENSE
Requires-Dist: rich>=14.0.0
Dynamic: license-file
